{
  "type": "ce",
  "attrType": 1,
  "fgoId": 998,

  "img": [
    { "weight": 1, "id": "img_ce", "src": "C0998.png" }
  ],

  "attribute": {
    "star": "star_3",
    "illustrator": "star-shadow-magician",
    "ce-type": "regular",
    "obtained": "event",
    "event": "chaldea-boys-collection-2021"
  },

  "data": {
    "name": {
      "en": "Vampire Masquerade Ball",
      "ja": "マスカレイド・オブ・ザ・ヴァンパイア",
      "zh": "吸血鬼假面舞会"
    }
  },

  "layout": [
    ["star", "illustrator"],
    ["ce-type", "obtained", "event"]
  ]
}
