{
  "type": "profile",
  "uid": "77:fgosvt",

  "attribute": {
    "class": "archer",
    "star": "star_5",
    "gender": "male",
    "origin": "historical-fact",
    "region": "europe",
    "alignment": "chaotic-good",
    "strength.parameter": "d",
    "endurance.parameter": "c",
    "agility.parameter": "c",
    "magic.parameter": "b",
    "luck.parameter": "d",
    "noble-phantasm.parameter": "ex",
    "character-setting": "sakurai-hikaru",
    "illustrator": "namaniku-atk",
    "character-voice": "inada-tetsu",
    "major-appearances": "fate-grand-order"
  },

  "data": {
    "name": {
      "en": "Nikola Tesla",
      "ja": "ニコラ・テスラ",
      "zh": "尼古拉·特斯拉"
    },
    "true-name": {
      "en": "Nikola Tesla",
      "ja": "ニコラ・テスラ",
      "zh": "尼古拉·特斯拉"
    },
    "height": {
      "en": "190cm",
      "ja": "190cm",
      "zh": "190cm"
    },
    "weight": {
      "en": "80kg",
      "ja": "80kg",
      "zh": "80kg"
    }
  },

  "layout": [
    ["star", "class"],
    ["true-name", "gender", "origin", "region", "alignment", "height", "weight"],
    ["strength.parameter", "endurance.parameter", "agility.parameter", "magic.parameter", "luck.parameter", "noble-phantasm.parameter"],
    ["character-setting", "illustrator", "character-voice", "major-appearances"]
  ]
}
