{
  "type": "profile",
  "uid": "27:fgosvt",

  "img": [
    { "weight": 1, "id": "img_s1", "src": "S0027a.png" },
    { "weight": 2, "id": "img_s2", "src": "S0027b.png" },
    { "weight": 3, "id": "img_s3", "src": "S0027c.png" },
    { "weight": 4, "id": "img_s4", "src": "S0027d.png" },
    { "weight": 5, "id": "img_april-fools", "src": "S0027e_april-fools.png" },
    { "weight": 6, "id": "img_psychedelic-wandering-tales", "src": "S0027f_psychedelic-wandering-tales.png" }
  ],

  "attribute": {
    "class": "rider",
    "star": "star_3",
    "gender": "female",
    "origin": ["gikeiki", "the-tale-of-the-heike"],
    "region": "japan",
    "alignment": "chaotic-neutral",
    "strength.parameter": "d",
    "endurance.parameter": "c",
    "agility.parameter": "ap",
    "magic.parameter": "b",
    "luck.parameter": "a",
    "noble-phantasm.parameter": "ap",
    "character-setting": ["higashide-yuuichirou", "nasu-kinoko"],
    "illustrator": "sakamoto-mineji",
    "character-voice": "hayami-saori",
    "major-appearances": "fate-grand-order",
    "related.profile": "ushiwakamaru-assassin"
  },

  "data": {
    "name": {
      "en": "Ushiwakamaru",
      "ja": "牛若丸",
      "zh": "牛若丸"
    },
    "true-name": {
      "en": "Ushiwakamaru (Minamoto no Yoshitsune)",
      "ja": "牛若丸（源義経）",
      "zh": "牛若丸（源义经）"
    },
    "height": {
      "en": "168cm",
      "ja": "168cm",
      "zh": "168cm"
    },
    "weight": {
      "en": "55kg",
      "ja": "55kg",
      "zh": "55kg"
    }
  },

  "layout": [
    ["star", "class"],
    ["true-name", "gender", "origin", "region", "alignment", "height", "weight"],
    ["strength.parameter", "endurance.parameter", "agility.parameter", "magic.parameter", "luck.parameter", "noble-phantasm.parameter"],
    ["character-setting", "illustrator", "character-voice", "major-appearances"],
    ["related.profile"]
  ]
}
